tests/__init__.py
tests/test_client.py
tests/test_acl/__init__.py
tests/test_acl/sample_job.py
tests/test_acl/test_acl.py
zipher/__init__.py
zipher/cli.py
zipher/client.py
zipher/conf.py
zipher/exceptions.py
zipher/models.py
zipher/utils.py
zipher/acl/__init__.py
zipher/acl/models.py
zipher/acl/zipher_installer.py
zipher_sdk-0.4.3.dist-info/LICENSE
zipher_sdk-0.4.3.dist-info/METADATA
zipher_sdk-0.4.3.dist-info/WHEEL
zipher_sdk-0.4.3.dist-info/entry_points.txt
zipher_sdk-0.4.3.dist-info/top_level.txt
zipher_sdk-0.4.3.dist-info/RECORD
