Metadata-Version: 2.1
Name: zipher-sdk
Version: 0.4.3
Summary: Python SDK for programmatic access to the Zipher API
Home-page: UNKNOWN
Author: Zipher Inc.
Author-email: yoav@zipher.cloud
License: UNKNOWN
Platform: UNKNOWN
Classifier: Programming Language :: Python :: 3
Classifier: License :: OSI Approved :: MIT License
Classifier: Operating System :: OS Independent
License-File: LICENSE
Requires-Dist: pydantic ==2.11.3
Requires-Dist: requests ==2.32.3
Requires-Dist: databricks-sdk ==0.52.0
